setup.py
modargs/__init__.py
modargs/args.py
python_modargs.egg-info/PKG-INFO
python_modargs.egg-info/SOURCES.txt
python_modargs.egg-info/dependency_links.txt
python_modargs.egg-info/top_level.txt