Metadata-Version: 1.0
Name: python-modargs
Version: 1.7
Summary: modargs is a simple command line argument parsing library that infers arguments from functions in a module
Home-page: http://pypi.python.org/pypi/python-modargs
Author: Zed A. Shaw
Author-email: zedshaw@zedshaw.com
License: UNKNOWN
Download-URL: http://pypi.python.org/pypi/python-modargs
Platform: UNKNOWN
